LKHpy.cpython-38-x86_64-linux-gnu.so
LKHpy-0.0.9.dist-info/top_level.txt
LKHpy-0.0.9.dist-info/RECORD
LKHpy-0.0.9.dist-info/LICENSE
LKHpy-0.0.9.dist-info/METADATA
LKHpy-0.0.9.dist-info/WHEEL
